rase/__init__.py
rase/increment_version.py
rase/version.py
rase-0.1.0.dist-info/DESCRIPTION.rst
rase-0.1.0.dist-info/METADATA
rase-0.1.0.dist-info/RECORD
rase-0.1.0.dist-info/WHEEL
rase-0.1.0.dist-info/entry_points.txt
rase-0.1.0.dist-info/metadata.json
rase-0.1.0.dist-info/top_level.txt
