Metadata-Version: 2.0
Name: rase
Version: 0.1.0
Summary: rase
Home-page: UNKNOWN
Author: Karel Brinda
Author-email: kbrinda@hsph.harvard.edu
License: MIT
Platform: UNKNOWN
Classifier: Development Status :: 4 - Beta
Classifier: Programming Language :: Python :: 3 :: Only
Classifier: Operating System :: Unix
Classifier: Environment :: Console
Classifier: License :: OSI Approved :: MIT License
Classifier: Intended Audience :: Science/Research
Classifier: Topic :: Scientific/Engineering :: Bio-Informatics
Requires-Dist: pysam
Requires-Dist: wheel
